im2im/__init__.py
im2im/api.py
im2im/code_generator.py
im2im/util.py
im2im/find_metadata/__init__.py
im2im/find_metadata/builtin_preset.py
im2im/find_metadata/preset_to_metadata.py
im2im/knowledge_graph_construction/ReadMe.md
im2im/knowledge_graph_construction/__init__.py
im2im/knowledge_graph_construction/constructor.py
im2im/knowledge_graph_construction/io.py
im2im/knowledge_graph_construction/knowledge_graph.json
im2im/knowledge_graph_construction/knowledge_graph.py
im2im/knowledge_graph_construction/knowledge_graph2.json
im2im/knowledge_graph_construction/edge_factories/PIL.py
im2im/knowledge_graph_construction/edge_factories/Pytorch.py
im2im/knowledge_graph_construction/edge_factories/ReadMe.md
im2im/knowledge_graph_construction/edge_factories/Tensorflow.py
im2im/knowledge_graph_construction/edge_factories/__init__.py
im2im/knowledge_graph_construction/edge_factories/inter_libs.py
im2im/knowledge_graph_construction/edge_factories/numpy.py
im2im/knowledge_graph_construction/edge_factories/type.py
im2im/knowledge_graph_construction/metedata/__init__.py
im2im/knowledge_graph_construction/metedata/type.py
im2im/knowledge_graph_construction/metedata/util.py
im2im-0.0.6.dist-info/licenses/LICENSE.txt
im2im-0.0.6.dist-info/METADATA
im2im-0.0.6.dist-info/WHEEL
im2im-0.0.6.dist-info/top_level.txt
im2im-0.0.6.dist-info/RECORD
