Metadata-Version: 2.4
Name: im2im
Version: 0.0.6
Summary: Automatically converting in-memory representations of images using a knowledge graph of type description.
Home-page: https://github.com/c3di/im2im
Author: "Fei Chen"
Author-email: boxchenfei@gmail.com
License: MIT
Project-URL: Source, https://github.com/c3di/im2im
Platform: any
Classifier: Development Status :: 4 - Beta
Classifier: Programming Language :: Python
Classifier: Programming Language :: Python :: 3.9
Classifier: Programming Language :: Python :: 3.10
Classifier: Programming Language :: Python :: 3.11
Requires-Python: <3.12,>=3.9
License-File: LICENSE.txt
Requires-Dist: importlib-metadata
Requires-Dist: networkx==3.2.1
Provides-Extra: testing
Requires-Dist: setuptools; extra == "testing"
Requires-Dist: pytest; extra == "testing"
Requires-Dist: pytest-cov; extra == "testing"
Dynamic: license-file
